AUTHORS
LICENSE
README.md
pyproject.toml
setup.py
pseudo_order_types/__init__.py
pseudo_order_types/pseudo_order_types.c
pseudo_order_types/pseudo_order_types.pyx
pseudo_order_types.egg-info/PKG-INFO
pseudo_order_types.egg-info/SOURCES.txt
pseudo_order_types.egg-info/dependency_links.txt
pseudo_order_types.egg-info/not-zip-safe
pseudo_order_types.egg-info/requires.txt
pseudo_order_types.egg-info/top_level.txt