Metadata-Version: 2.1
Name: pseudo-order-types
Version: 0.1.1
Summary: Generate all pseudo order types for small point sets in the plane
Home-page: https://github.com/kliem/pseudo_order_types
Author: Jonathan Kliem
Author-email: jonathan.kliem@fu-berlin.de
License: GPLv3
Platform: UNKNOWN
Classifier: Development Status :: 2 - Pre-Alpha
Classifier: Intended Audience :: Science/Research
Classifier: License :: OSI Approved :: GNU General Public License v3 (GPLv3)
Classifier: Programming Language :: Python :: 3
Classifier: Topic :: Scientific/Engineering :: Mathematics
Requires-Python: >=3.6
